clkdiv.v
module clkdiv(
	clk_i,
	rstn_i,
	sel_i,
	dclk_o
);
input  wire 	 clk_i;
input  wire 	 rstn_i;
input  wire [1:0] sel_i;
output reg	 dclk_o;
	
reg [7:0] cnt;

always @(posedge clk_i or negedge rstn_i) //negendge
begin
	if (!rstn_i)
		cnt <= 8'h00;
		
	else
	begin
		cnt <= cnt + 1;
	end
end

always @(*)
begin
	case(sel_i)
	2'b00: dclk_o = cnt[7];
	2'b01: dclk_o = cnt[6];
	2'b10: dclk_o = cnt[5];
	2'b11: dclk_o = cnt[4];
	default: dclk_o = 1'b0;
	endcase
end

endmodule

top.v
module top(
	clk_i,
	rstn_i,
	sel_i,
	dclk_o,
	en_i 
);

input wire clk_i;
input wire rstn_i;
input wire [1:0] sel_i;
input wire en_i;
output wire dclk_o;

wire dclk;
clkdiv clkdiv_inst(
	.clk_i(clk_i),
	. rstn_i(rstn_i),
	. sel_i(sel_i),
	 .dclk_o(dclk)
);

assign dclk = dclk&en_i;

endmodule

//latch
//wire en;
//wire d;
//reg q;

//assign q = en ? d : q

tb.v
`timescale 1ns/10ps
module tb();

reg clk;
reg rstn;
reg [1:0] sel;
reg en;
wire dclk;

top top_inst(
	.clk_i(clk),
	.rstn_i(rstn),
	.sel_i(sel),
	.dclk_o(dclk),
	.en_i(en)
);

realtime period = 10;
realtime t;

always #(period/2) clk = !clk;

initial begin
	$dumpvars;
	clk = 1'b0;
	sel = 2'b00;
	en = 1'b1;	
	
	rstn = 1'b0;
	#(100);
	rstn = 1'b1;
	
#(1000);
$finish;	
	@(posedge dclk);
	t = $realtime;
	@(posedge dclk);
	t = $realtime - t;

	//if(t == period*(2ˆ(7 - sel)))
	//	$display("SUCCESS");
	//else
	//	$display("ERROR");
	$finish;
end

endmodule

dump.vcd
$date
	Sat Mar  5 17:35:33 2022
$end
$version
	Icarus Verilog
$end
$timescale
	10ps
$end
$scope module tb $end
$var wire 1 ! dclk $end
$var reg 1 " clk $end
$var reg 1 # en $end
$var reg 1 $ rstn $end
$var reg 2 % sel [1:0] $end
$var real 1 & period $end
$var real 1 ' t $end
$scope module top_inst $end
$var wire 1 " clk_i $end
$var wire 1 ( dclk $end
$var wire 1 ! dclk_o $end
$var wire 1 # en_i $end
$var wire 1 $ rstn_i $end
$var wire 2 ) sel_i [1:0] $end
$scope module clkdiv_inst $end
$var wire 1 " clk_i $end
$var wire 1 $ rstn_i $end
$var wire 2 * sel_i [1:0] $end
$var reg 8 + cnt [7:0] $end
$var reg 1 , dclk_o $end
$upscope $end
$upscope $end
$upscope $end
$enddefinitions $end
#0
$dumpvars
0,
b0 +
b0 *
b0 )
x(
r0 '
r10 &
b0 %
0$
1#
0"
z!
$end
#500
1"
#1000
0"
#1500
1"
#2000
0"
#2500
1"
#3000
0"
#3500
1"
#4000
0"
#4500
1"
#5000
0"
#5500
1"
#6000
0"
#6500
1"
#7000
0"
#7500
1"
#8000
0"
#8500
1"
#9000
0"
#9500
1"
#10000
0"
1$
#10500
b1 +
1"
#11000
0"
#11500
b10 +
1"
#12000
0"
#12500
b11 +
1"
#13000
0"
#13500
b100 +
1"
#14000
0"
#14500
b101 +
1"
#15000
0"
#15500
b110 +
1"
#16000
0"
#16500
b111 +
1"
#17000
0"
#17500
b1000 +
1"
#18000
0"
#18500
b1001 +
1"
#19000
0"
#19500
b1010 +
1"
#20000
0"
#20500
b1011 +
1"
#21000
0"
#21500
b1100 +
1"
#22000
0"
#22500
b1101 +
1"
#23000
0"
#23500
b1110 +
1"
#24000
0"
#24500
b1111 +
1"
#25000
0"
#25500
b10000 +
1"
#26000
0"
#26500
b10001 +
1"
#27000
0"
#27500
b10010 +
1"
#28000
0"
#28500
b10011 +
1"
#29000
0"
#29500
b10100 +
1"
#30000
0"
#30500
b10101 +
1"
#31000
0"
#31500
b10110 +
1"
#32000
0"
#32500
b10111 +
1"
#33000
0"
#33500
b11000 +
1"
#34000
0"
#34500
b11001 +
1"
#35000
0"
#35500
b11010 +
1"
#36000
0"
#36500
b11011 +
1"
#37000
0"
#37500
b11100 +
1"
#38000
0"
#38500
b11101 +
1"
#39000
0"
#39500
b11110 +
1"
#40000
0"
#40500
b11111 +
1"
#41000
0"
#41500
b100000 +
1"
#42000
0"
#42500
b100001 +
1"
#43000
0"
#43500
b100010 +
1"
#44000
0"
#44500
b100011 +
1"
#45000
0"
#45500
b100100 +
1"
#46000
0"
#46500
b100101 +
1"
#47000
0"
#47500
b100110 +
1"
#48000
0"
#48500
b100111 +
1"
#49000
0"
#49500
b101000 +
1"
#50000
0"
#50500
b101001 +
1"
#51000
0"
#51500
b101010 +
1"
#52000
0"
#52500
b101011 +
1"
#53000
0"
#53500
b101100 +
1"
#54000
0"
#54500
b101101 +
1"
#55000
0"
#55500
b101110 +
1"
#56000
0"
#56500
b101111 +
1"
#57000
0"
#57500
b110000 +
1"
#58000
0"
#58500
b110001 +
1"
#59000
0"
#59500
b110010 +
1"
#60000
0"
#60500
b110011 +
1"
#61000
0"
#61500
b110100 +
1"
#62000
0"
#62500
b110101 +
1"
#63000
0"
#63500
b110110 +
1"
#64000
0"
#64500
b110111 +
1"
#65000
0"
#65500
b111000 +
1"
#66000
0"
#66500
b111001 +
1"
#67000
0"
#67500
b111010 +
1"
#68000
0"
#68500
b111011 +
1"
#69000
0"
#69500
b111100 +
1"
#70000
0"
#70500
b111101 +
1"
#71000
0"
#71500
b111110 +
1"
#72000
0"
#72500
b111111 +
1"
#73000
0"
#73500
b1000000 +
1"
#74000
0"
#74500
b1000001 +
1"
#75000
0"
#75500
b1000010 +
1"
#76000
0"
#76500
b1000011 +
1"
#77000
0"
#77500
b1000100 +
1"
#78000
0"
#78500
b1000101 +
1"
#79000
0"
#79500
b1000110 +
1"
#80000
0"
#80500
b1000111 +
1"
#81000
0"
#81500
b1001000 +
1"
#82000
0"
#82500
b1001001 +
1"
#83000
0"
#83500
b1001010 +
1"
#84000
0"
#84500
b1001011 +
1"
#85000
0"
#85500
b1001100 +
1"
#86000
0"
#86500
b1001101 +
1"
#87000
0"
#87500
b1001110 +
1"
#88000
0"
#88500
b1001111 +
1"
#89000
0"
#89500
b1010000 +
1"
#90000
0"
#90500
b1010001 +
1"
#91000
0"
#91500
b1010010 +
1"
#92000
0"
#92500
b1010011 +
1"
#93000
0"
#93500
b1010100 +
1"
#94000
0"
#94500
b1010101 +
1"
#95000
0"
#95500
b1010110 +
1"
#96000
0"
#96500
b1010111 +
1"
#97000
0"
#97500
b1011000 +
1"
#98000
0"
#98500
b1011001 +
1"
#99000
0"
#99500
b1011010 +
1"
#100000
0"
#100500
b1011011 +
1"
#101000
0"
#101500
b1011100 +
1"
#102000
0"
#102500
b1011101 +
1"
#103000
0"
#103500
b1011110 +
1"
#104000
0"
#104500
b1011111 +
1"
#105000
0"
#105500
b1100000 +
1"
#106000
0"
#106500
b1100001 +
1"
#107000
0"
#107500
b1100010 +
1"
#108000
0"
#108500
b1100011 +
1"
#109000
0"
#109500
b1100100 +
1"
